allauth/__init__.py
allauth/app_settings.py
allauth/decorators.py
allauth/exceptions.py
allauth/models.py
allauth/ratelimit.py
allauth/urls.py
allauth/utils.py
allauth/account/__init__.py
allauth/account/adapter.py
allauth/account/admin.py
allauth/account/app_settings.py
allauth/account/apps.py
allauth/account/auth_backends.py
allauth/account/authentication.py
allauth/account/checks.py
allauth/account/decorators.py
allauth/account/fields.py
allauth/account/forms.py
allauth/account/managers.py
allauth/account/middleware.py
allauth/account/mixins.py
allauth/account/models.py
allauth/account/reauthentication.py
allauth/account/signals.py
allauth/account/stages.py
allauth/account/urls.py
allauth/account/utils.py
allauth/account/views.py
allauth/account/internal/__init__.py
allauth/account/internal/decorators.py
allauth/account/internal/emailkit.py
allauth/account/internal/stagekit.py
allauth/account/internal/userkit.py
allauth/account/internal/flows/__init__.py
allauth/account/internal/flows/code_verification.py
allauth/account/internal/flows/email_verification.py
allauth/account/internal/flows/email_verification_by_code.py
allauth/account/internal/flows/login.py
allauth/account/internal/flows/login_by_code.py
allauth/account/internal/flows/logout.py
allauth/account/internal/flows/manage_email.py
allauth/account/internal/flows/password_change.py
allauth/account/internal/flows/password_reset.py
allauth/account/internal/flows/password_reset_by_code.py
allauth/account/internal/flows/phone_verification.py
allauth/account/internal/flows/reauthentication.py
allauth/account/internal/flows/signup.py
allauth/account/management/__init__.py
allauth/account/management/commands/__init__.py
allauth/account/management/commands/account_unsetmultipleprimaryemails.py
allauth/account/migrations/0001_initial.py
allauth/account/migrations/0002_email_max_length.py
allauth/account/migrations/0003_alter_emailaddress_create_unique_verified_email.py
allauth_fork_zango-65.10.3.dist-info/licenses/AUTHORS
allauth_fork_zango-65.10.3.dist-info/licenses/LICENSE
allauth_fork_zango-65.10.3.dist-info/METADATA
allauth_fork_zango-65.10.3.dist-info/WHEEL
allauth_fork_zango-65.10.3.dist-info/top_level.txt
allauth_fork_zango-65.10.3.dist-info/RECORD
