Metadata-Version: 2.4
Name: allauth-fork-zango
Version: 65.10.3
Summary: Fork with changes for zango
Author-email: Zelthy <maintainers@zelthy.com>
License: MIT
Project-URL: Homepage, https://github.com/Healthlane-Technologies/django-allauth/tree/zango_allauth
Project-URL: Release notes, https://github.com/Healthlane-Technologies/django-allauth/releases
Project-URL: Source, https://github.com/Healthlane-Technologies/django-allauth/tree/zango_allauth
Project-URL: Bug Tracker, https://github.com/Healthlane-Technologies/django-allauth/issues
Classifier: Development Status :: 5 - Production/Stable
Classifier: Intended Audience :: Developers
Classifier: Topic :: Software Development :: Libraries :: Python Modules
Classifier: Environment :: Web Environment
Classifier: Topic :: Internet
Classifier: License :: OSI Approved :: MIT License
Classifier: Operating System :: OS Independent
Classifier: Programming Language :: Python
Classifier: Programming Language :: Python :: 3
Classifier: Programming Language :: Python :: 3.8
Classifier: Programming Language :: Python :: 3.9
Classifier: Programming Language :: Python :: 3.10
Classifier: Programming Language :: Python :: 3.11
Classifier: Programming Language :: Python :: 3.12
Classifier: Programming Language :: Python :: 3.13
Classifier: Framework :: Django
Classifier: Framework :: Django :: 4.2
Classifier: Framework :: Django :: 5.0
Classifier: Framework :: Django :: 5.1
Classifier: Framework :: Django :: 5.2
Requires-Python: >=3.8
License-File: LICENSE
License-File: AUTHORS
Requires-Dist: Django==4.2.16
Requires-Dist: asgiref>=3.8.1
Provides-Extra: idp-oidc
Requires-Dist: oauthlib<4,>=3.3.0; extra == "idp-oidc"
Requires-Dist: pyjwt[crypto]<3,>=2.0; extra == "idp-oidc"
Provides-Extra: mfa
Requires-Dist: qrcode<9,>=7.0.0; extra == "mfa"
Requires-Dist: fido2<3,>=1.1.2; extra == "mfa"
Provides-Extra: openid
Requires-Dist: python3-openid<4,>=3.0.8; extra == "openid"
Provides-Extra: saml
Requires-Dist: python3-saml<2.0.0,>=1.15.0; extra == "saml"
Provides-Extra: steam
Requires-Dist: python3-openid<4,>=3.0.8; extra == "steam"
Provides-Extra: socialaccount
Requires-Dist: oauthlib<4,>=3.3.0; extra == "socialaccount"
Requires-Dist: requests<3,>=2.0.0; extra == "socialaccount"
Requires-Dist: pyjwt[crypto]<3,>=2.0; extra == "socialaccount"
Dynamic: license-file
